lupin3/__init__.py
lupin3/autoinstall.py
lupin3/dataprocess.py
lupin3/func.py
lupin3/ml.py
lupin3/nlp.py
lupin3/plt.py
lupin3/setup.py
lupin3-0.0.33.dist-info/METADATA
lupin3-0.0.33.dist-info/WHEEL
lupin3-0.0.33.dist-info/top_level.txt
lupin3-0.0.33.dist-info/RECORD
