Metadata-Version: 2.1
Name: lupin3
Version: 0.0.33
Summary: for myself
Home-page: https://github.com/RoRyou/Lupin3
Author: Roryou
Author-email: luliang_penn@live.com
Classifier: Programming Language :: Python :: 3
Classifier: License :: OSI Approved :: MIT License
Classifier: Operating System :: OS Independent
